SpaHDmap/__init__.py
SpaHDmap/train.py
SpaHDmap/data/__init__.py
SpaHDmap/data/bsp.py
SpaHDmap/data/color_normalize.py
SpaHDmap/data/data_util.py
SpaHDmap/data/dataset.py
SpaHDmap/data/sparkx.py
SpaHDmap/model/__init__.py
SpaHDmap/model/models.py
SpaHDmap/utils/__init__.py
SpaHDmap/utils/clustering.py
SpaHDmap/utils/color.csv
SpaHDmap/utils/utils.py
SpaHDmap/utils/visualize.py
SpaHDmap-0.1.4.dist-info/LICENSE
SpaHDmap-0.1.4.dist-info/METADATA
SpaHDmap-0.1.4.dist-info/WHEEL
SpaHDmap-0.1.4.dist-info/top_level.txt
SpaHDmap-0.1.4.dist-info/RECORD
