Metadata-Version: 2.1
Name: SpaHDmap
Version: 0.1.4
Summary: Interpretable high-definition dimension reduction of spatial transcriptomics data by SpaHDmap
Author-email: Kun Qian <kunqian@stu.pku.edu.cn>, Junjie Tang <junjie.tang@pku.edu.cn>
Maintainer-email: Kun Qian <kunqian@stu.pku.edu.cn>
License: MIT License
Project-URL: Homepage, https://github.com/sldyns/SpaHDmap
Keywords: spatial transcriptomics,bioinformatics,dimension reduction,deep learning
Classifier: Development Status :: 5 - Production/Stable
Classifier: Intended Audience :: Developers
Classifier: Intended Audience :: Science/Research
Classifier: Natural Language :: English
Classifier: Operating System :: POSIX :: Linux
Classifier: Operating System :: MacOS :: MacOS X
Classifier: Operating System :: Microsoft :: Windows
Classifier: Typing :: Typed
Classifier: Programming Language :: Python :: 3
Classifier: Programming Language :: Python :: 3 :: Only
Classifier: Programming Language :: Python :: 3.10
Classifier: Programming Language :: Python :: 3.11
Classifier: Programming Language :: Python :: 3.12
Classifier: Topic :: Scientific/Engineering :: Bio-Informatics
Classifier: Topic :: Scientific/Engineering :: Mathematics
Requires-Python: >=3.10
License-File: LICENSE
Requires-Dist: numpy <2,>=1.25.2
Requires-Dist: cython >=0.29.24
Requires-Dist: torch >=1.11.0
Requires-Dist: scikit-learn >=1.0
Requires-Dist: dask ==2024.8.0
Requires-Dist: matplotlib
Requires-Dist: tqdm
Requires-Dist: h5py
Requires-Dist: scanpy
Requires-Dist: pandas
Requires-Dist: scikit-image
Requires-Dist: opencv-python
Requires-Dist: imagecodecs
Requires-Dist: scipy
Requires-Dist: scikit-network
Requires-Dist: zarr <3.0.0,>=2.6.1
Requires-Dist: anndata <0.11.0,>=0.9.0
Requires-Dist: squidpy <1.6.3,>=1.6.0
Provides-Extra: docs
Requires-Dist: sphinx >=8.0.1 ; extra == 'docs'
Requires-Dist: furo >=2024.3.31 ; extra == 'docs'
Requires-Dist: myst-parser >=2.2.0 ; extra == 'docs'
Requires-Dist: nbsphinx >=0.8.11 ; extra == 'docs'
Requires-Dist: sphinx-tippy >=0.4.1 ; extra == 'docs'
Requires-Dist: sphinx-autodoc-typehints >=1.10.3 ; extra == 'docs'
Requires-Dist: sphinx-copybutton >=0.5.0 ; extra == 'docs'
Requires-Dist: sphinx-design >=0.3.0 ; extra == 'docs'
